{
    "segments": [
        {
            "gridIndex": "0x440",
            "parameterIndex": 0
        },
        {
            "gridIndex": "0x441",
            "parameterIndex": 1
        },
        {
            "gridIndex": "0x442",
            "parameterIndex": 1
        },
        {
            "gridIndex": "0x443",
            "parameterIndex": 1
        },
        {
            "gridIndex": "0x444",
            "parameterIndex": 2
        },
        {
            "gridIndex": "0x4C0",
            "parameterIndex": 3
        },
        {
            "gridIndex": "0x4C4",
            "parameterIndex": 4
        },
        {
            "gridIndex": "0x540",
            "parameterIndex": 3
        },
        {
            "gridIndex": "0x544",
            "parameterIndex": 2
        },
        {
            "gridIndex": "0x545",
            "parameterIndex": 1
        },
        {
            "gridIndex": "0x546",
            "parameterIndex": 1
        },
        {
            "gridIndex": "0x547",
            "parameterIndex": 1
        },
        {
            "gridIndex": "0x548",
            "parameterIndex": 1
        },
        {
            "gridIndex": "0x549",
            "parameterIndex": 1
        },
        {
            "gridIndex": "0x54A",
            "parameterIndex": 1
        },
        {
            "gridIndex": "0x54B",
            "parameterIndex": 1
        },
        {
            "gridIndex": "0x54C",
            "parameterIndex": 1
        },
        {
            "gridIndex": "0x54D",
            "parameterIndex": 1
        },
        {
            "gridIndex": "0x54E",
            "parameterIndex": 1
        },
        {
            "gridIndex": "0x54F",
            "parameterIndex": 1
        },
        {
            "gridIndex": "0x550",
            "parameterIndex": 1
        },
        {
            "gridIndex": "0x551",
            "parameterIndex": 2
        },
        {
            "gridIndex": "0x5C0",
            "parameterIndex": 3
        },
        {
            "gridIndex": "0x5D1",
            "parameterIndex": 4
        },
        {
            "gridIndex": "0x640",
            "parameterIndex": 3
        },
        {
            "gridIndex": "0x650",
            "parameterIndex": 5
        },
        {
            "gridIndex": "0x651",
            "parameterIndex": 4
        },
        {
            "gridIndex": "0x6C0",
            "parameterIndex": 3
        },
        {
            "gridIndex": "0x6D0",
            "parameterIndex": 4
        },
        {
            "gridIndex": "0x740",
            "parameterIndex": 3
        },
        {
            "gridIndex": "0x750",
            "parameterIndex": 4
        },
        {
            "gridIndex": "0x7C0",
            "parameterIndex": 3
        },
        {
            "gridIndex": "0x7D0",
            "parameterIndex": 4
        },
        {
            "gridIndex": "0x83F",
            "parameterIndex": 6
        },
        {
            "gridIndex": "0x840",
            "parameterIndex": 7
        },
        {
            "gridIndex": "0x850",
            "parameterIndex": 4
        },
        {
            "gridIndex": "0x8BE",
            "parameterIndex": 6
        },
        {
            "gridIndex": "0x8BF",
            "parameterIndex": 7
        },
        {
            "gridIndex": "0x8D0",
            "parameterIndex": 4
        },
        {
            "gridIndex": "0x930",
            "parameterIndex": 0
        },
        {
            "gridIndex": "0x931",
            "parameterIndex": 1
        },
        {
            "gridIndex": "0x932",
            "parameterIndex": 1
        },
        {
            "gridIndex": "0x933",
            "parameterIndex": 1
        },
        {
            "gridIndex": "0x934",
            "parameterIndex": 1
        },
        {
            "gridIndex": "0x935",
            "parameterIndex": 1
        },
        {
            "gridIndex": "0x936",
            "parameterIndex": 1
        },
        {
            "gridIndex": "0x937",
            "parameterIndex": 1
        },
        {
            "gridIndex": "0x938",
            "parameterIndex": 1
        },
        {
            "gridIndex": "0x939",
            "parameterIndex": 1
        },
        {
            "gridIndex": "0x93A",
            "parameterIndex": 1
        },
        {
            "gridIndex": "0x93B",
            "parameterIndex": 1
        },
        {
            "gridIndex": "0x93C",
            "parameterIndex": 1
        },
        {
            "gridIndex": "0x93D",
            "parameterIndex": 1
        },
        {
            "gridIndex": "0x93E",
            "parameterIndex": 7
        },
        {
            "gridIndex": "0x950",
            "parameterIndex": 4
        },
        {
            "gridIndex": "0x9B0",
            "parameterIndex": 3
        },
        {
            "gridIndex": "0x9D0",
            "parameterIndex": 4
        },
        {
            "gridIndex": "0xA24",
            "parameterIndex": 1
        },
        {
            "gridIndex": "0xA25",
            "parameterIndex": 1
        },
        {
            "gridIndex": "0xA26",
            "parameterIndex": 1
        },
        {
            "gridIndex": "0xA27",
            "parameterIndex": 1
        },
        {
            "gridIndex": "0xA28",
            "parameterIndex": 1
        },
        {
            "gridIndex": "0xA29",
            "parameterIndex": 1
        },
        {
            "gridIndex": "0xA30",
            "parameterIndex": 3
        },
        {
            "gridIndex": "0xA50",
            "parameterIndex": 4
        },
        {
            "gridIndex": "0xAA3",
            "parameterIndex": 6
        },
        {
            "gridIndex": "0xAA4",
            "parameterIndex": 7
        },
        {
            "gridIndex": "0xAA9",
            "parameterIndex": 8
        },
        {
            "gridIndex": "0xAAA",
            "parameterIndex": 9
        },
        {
            "gridIndex": "0xAAF",
            "parameterIndex": 6
        },
        {
            "gridIndex": "0xAB0",
            "parameterIndex": 7
        },
        {
            "gridIndex": "0xAD0",
            "parameterIndex": 4
        },
        {
            "gridIndex": "0xB1E",
            "parameterIndex": 0
        },
        {
            "gridIndex": "0xB1F",
            "parameterIndex": 1
        },
        {
            "gridIndex": "0xB22",
            "parameterIndex": 6
        },
        {
            "gridIndex": "0xB23",
            "parameterIndex": 7
        },
        {
            "gridIndex": "0xB2A",
            "parameterIndex": 8
        },
        {
            "gridIndex": "0xB2B",
            "parameterIndex": 9
        },
        {
            "gridIndex": "0xB2E",
            "parameterIndex": 6
        },
        {
            "gridIndex": "0xB2F",
            "parameterIndex": 7
        },
        {
            "gridIndex": "0xB50",
            "parameterIndex": 4
        },
        {
            "gridIndex": "0xB9E",
            "parameterIndex": 3
        },
        {
            "gridIndex": "0xB9F",
            "parameterIndex": 8
        },
        {
            "gridIndex": "0xBA0",
            "parameterIndex": 1
        },
        {
            "gridIndex": "0xBA1",
            "parameterIndex": 1
        },
        {
            "gridIndex": "0xBA2",
            "parameterIndex": 7
        },
        {
            "gridIndex": "0xBAB",
            "parameterIndex": 8
        },
        {
            "gridIndex": "0xBAC",
            "parameterIndex": 1
        },
        {
            "gridIndex": "0xBAD",
            "parameterIndex": 1
        },
        {
            "gridIndex": "0xBAE",
            "parameterIndex": 7
        },
        {
            "gridIndex": "0xBD0",
            "parameterIndex": 4
        },
        {
            "gridIndex": "0xC1E",
            "parameterIndex": 3
        },
        {
            "gridIndex": "0xC50",
            "parameterIndex": 4
        },
        {
            "gridIndex": "0xC9E",
            "parameterIndex": 3
        },
        {
            "gridIndex": "0xCD0",
            "parameterIndex": 4
        },
        {
            "gridIndex": "0xD1A",
            "parameterIndex": 0
        },
        {
            "gridIndex": "0xD1B",
            "parameterIndex": 1
        },
        {
            "gridIndex": "0xD1C",
            "parameterIndex": 1
        },
        {
            "gridIndex": "0xD1D",
            "parameterIndex": 1
        },
        {
            "gridIndex": "0xD1E",
            "parameterIndex": 0
        },
        {
            "gridIndex": "0xD50",
            "parameterIndex": 4
        },
        {
            "gridIndex": "0xD9A",
            "parameterIndex": 3
        },
        {
            "gridIndex": "0xDD0",
            "parameterIndex": 4
        },
        {
            "gridIndex": "0xE1A",
            "parameterIndex": 3
        },
        {
            "gridIndex": "0xE50",
            "parameterIndex": 4
        },
        {
            "gridIndex": "0xE9A",
            "parameterIndex": 3
        },
        {
            "gridIndex": "0xED0",
            "parameterIndex": 4
        },
        {
            "gridIndex": "0xF1A",
            "parameterIndex": 3
        },
        {
            "gridIndex": "0xF50",
            "parameterIndex": 4
        },
        {
            "gridIndex": "0xF9A",
            "parameterIndex": 3
        },
        {
            "gridIndex": "0xFD0",
            "parameterIndex": 4
        },
        {
            "gridIndex": "0x101A",
            "parameterIndex": 3
        },
        {
            "gridIndex": "0x1050",
            "parameterIndex": 4
        },
        {
            "gridIndex": "0x109A",
            "parameterIndex": 10
        },
        {
            "gridIndex": "0x109B",
            "parameterIndex": 11
        },
        {
            "gridIndex": "0x109C",
            "parameterIndex": 11
        },
        {
            "gridIndex": "0x109D",
            "parameterIndex": 11
        },
        {
            "gridIndex": "0x109E",
            "parameterIndex": 10
        },
        {
            "gridIndex": "0x10D0",
            "parameterIndex": 8
        },
        {
            "gridIndex": "0x10D1",
            "parameterIndex": 4
        },
        {
            "gridIndex": "0x111E",
            "parameterIndex": 3
        },
        {
            "gridIndex": "0x1151",
            "parameterIndex": 4
        },
        {
            "gridIndex": "0x119E",
            "parameterIndex": 3
        },
        {
            "gridIndex": "0x11D1",
            "parameterIndex": 4
        },
        {
            "gridIndex": "0x121E",
            "parameterIndex": 3
        },
        {
            "gridIndex": "0x1251",
            "parameterIndex": 4
        },
        {
            "gridIndex": "0x129E",
            "parameterIndex": 10
        },
        {
            "gridIndex": "0x129F",
            "parameterIndex": 11
        },
        {
            "gridIndex": "0x12A0",
            "parameterIndex": 11
        },
        {
            "gridIndex": "0x12A1",
            "parameterIndex": 11
        },
        {
            "gridIndex": "0x12A2",
            "parameterIndex": 11
        },
        {
            "gridIndex": "0x12A3",
            "parameterIndex": 11
        },
        {
            "gridIndex": "0x12A4",
            "parameterIndex": 11
        },
        {
            "gridIndex": "0x12A5",
            "parameterIndex": 11
        },
        {
            "gridIndex": "0x12A6",
            "parameterIndex": 11
        },
        {
            "gridIndex": "0x12A7",
            "parameterIndex": 11
        },
        {
            "gridIndex": "0x12A8",
            "parameterIndex": 11
        },
        {
            "gridIndex": "0x12A9",
            "parameterIndex": 11
        },
        {
            "gridIndex": "0x12AA",
            "parameterIndex": 11
        },
        {
            "gridIndex": "0x12AB",
            "parameterIndex": 11
        },
        {
            "gridIndex": "0x12AC",
            "parameterIndex": 11
        },
        {
            "gridIndex": "0x12AD",
            "parameterIndex": 11
        },
        {
            "gridIndex": "0x12AE",
            "parameterIndex": 11
        },
        {
            "gridIndex": "0x12AF",
            "parameterIndex": 10
        },
        {
            "gridIndex": "0x12D1",
            "parameterIndex": 4
        },
        {
            "gridIndex": "0x132F",
            "parameterIndex": 3
        },
        {
            "gridIndex": "0x133D",
            "parameterIndex": 5
        },
        {
            "gridIndex": "0x133E",
            "parameterIndex": 11
        },
        {
            "gridIndex": "0x133F",
            "parameterIndex": 11
        },
        {
            "gridIndex": "0x1340",
            "parameterIndex": 11
        },
        {
            "gridIndex": "0x1341",
            "parameterIndex": 11
        },
        {
            "gridIndex": "0x1342",
            "parameterIndex": 11
        },
        {
            "gridIndex": "0x1343",
            "parameterIndex": 11
        },
        {
            "gridIndex": "0x1344",
            "parameterIndex": 11
        },
        {
            "gridIndex": "0x1345",
            "parameterIndex": 11
        },
        {
            "gridIndex": "0x1346",
            "parameterIndex": 11
        },
        {
            "gridIndex": "0x1347",
            "parameterIndex": 11
        },
        {
            "gridIndex": "0x1348",
            "parameterIndex": 11
        },
        {
            "gridIndex": "0x1349",
            "parameterIndex": 11
        },
        {
            "gridIndex": "0x134A",
            "parameterIndex": 11
        },
        {
            "gridIndex": "0x134B",
            "parameterIndex": 11
        },
        {
            "gridIndex": "0x134C",
            "parameterIndex": 11
        },
        {
            "gridIndex": "0x134D",
            "parameterIndex": 11
        },
        {
            "gridIndex": "0x134E",
            "parameterIndex": 11
        },
        {
            "gridIndex": "0x134F",
            "parameterIndex": 11
        },
        {
            "gridIndex": "0x1350",
            "parameterIndex": 11
        },
        {
            "gridIndex": "0x1351",
            "parameterIndex": 12
        },
        {
            "gridIndex": "0x13AF",
            "parameterIndex": 3
        },
        {
            "gridIndex": "0x13BD",
            "parameterIndex": 12
        },
        {
            "gridIndex": "0x142F",
            "parameterIndex": 3
        },
        {
            "gridIndex": "0x143D",
            "parameterIndex": 4
        },
        {
            "gridIndex": "0x14AF",
            "parameterIndex": 3
        },
        {
            "gridIndex": "0x14BD",
            "parameterIndex": 4
        },
        {
            "gridIndex": "0x152F",
            "parameterIndex": 3
        },
        {
            "gridIndex": "0x153D",
            "parameterIndex": 4
        },
        {
            "gridIndex": "0x15AF",
            "parameterIndex": 3
        },
        {
            "gridIndex": "0x15BD",
            "parameterIndex": 8
        },
        {
            "gridIndex": "0x15BE",
            "parameterIndex": 4
        },
        {
            "gridIndex": "0x162F",
            "parameterIndex": 3
        },
        {
            "gridIndex": "0x163E",
            "parameterIndex": 4
        },
        {
            "gridIndex": "0x16AF",
            "parameterIndex": 3
        },
        {
            "gridIndex": "0x16BE",
            "parameterIndex": 2
        },
        {
            "gridIndex": "0x16BF",
            "parameterIndex": 1
        },
        {
            "gridIndex": "0x16C0",
            "parameterIndex": 1
        },
        {
            "gridIndex": "0x16C1",
            "parameterIndex": 1
        },
        {
            "gridIndex": "0x16C2",
            "parameterIndex": 1
        },
        {
            "gridIndex": "0x16C3",
            "parameterIndex": 1
        },
        {
            "gridIndex": "0x16C4",
            "parameterIndex": 1
        },
        {
            "gridIndex": "0x16C5",
            "parameterIndex": 1
        },
        {
            "gridIndex": "0x16C6",
            "parameterIndex": 1
        },
        {
            "gridIndex": "0x16C7",
            "parameterIndex": 1
        },
        {
            "gridIndex": "0x16C8",
            "parameterIndex": 1
        },
        {
            "gridIndex": "0x16C9",
            "parameterIndex": 1
        },
        {
            "gridIndex": "0x16CA",
            "parameterIndex": 1
        },
        {
            "gridIndex": "0x16CB",
            "parameterIndex": 1
        },
        {
            "gridIndex": "0x16CC",
            "parameterIndex": 1
        },
        {
            "gridIndex": "0x16CD",
            "parameterIndex": 1
        },
        {
            "gridIndex": "0x16CE",
            "parameterIndex": 1
        },
        {
            "gridIndex": "0x16CF",
            "parameterIndex": 2
        },
        {
            "gridIndex": "0x172F",
            "parameterIndex": 3
        },
        {
            "gridIndex": "0x174F",
            "parameterIndex": 4
        },
        {
            "gridIndex": "0x17AF",
            "parameterIndex": 3
        },
        {
            "gridIndex": "0x17CF",
            "parameterIndex": 4
        },
        {
            "gridIndex": "0x182F",
            "parameterIndex": 3
        },
        {
            "gridIndex": "0x184F",
            "parameterIndex": 4
        },
        {
            "gridIndex": "0x18AF",
            "parameterIndex": 3
        },
        {
            "gridIndex": "0x18CF",
            "parameterIndex": 4
        },
        {
            "gridIndex": "0x192F",
            "parameterIndex": 3
        },
        {
            "gridIndex": "0x194F",
            "parameterIndex": 4
        },
        {
            "gridIndex": "0x19AF",
            "parameterIndex": 3
        },
        {
            "gridIndex": "0x19CF",
            "parameterIndex": 4
        },
        {
            "gridIndex": "0x1A2F",
            "parameterIndex": 3
        },
        {
            "gridIndex": "0x1A4F",
            "parameterIndex": 4
        },
        {
            "gridIndex": "0x1AAF",
            "parameterIndex": 3
        },
        {
            "gridIndex": "0x1ACF",
            "parameterIndex": 4
        },
        {
            "gridIndex": "0x1B2F",
            "parameterIndex": 3
        },
        {
            "gridIndex": "0x1B3C",
            "parameterIndex": 5
        },
        {
            "gridIndex": "0x1B3D",
            "parameterIndex": 11
        },
        {
            "gridIndex": "0x1B3E",
            "parameterIndex": 11
        },
        {
            "gridIndex": "0x1B3F",
            "parameterIndex": 11
        },
        {
            "gridIndex": "0x1B40",
            "parameterIndex": 11
        },
        {
            "gridIndex": "0x1B41",
            "parameterIndex": 11
        },
        {
            "gridIndex": "0x1B42",
            "parameterIndex": 11
        },
        {
            "gridIndex": "0x1B43",
            "parameterIndex": 10
        },
        {
            "gridIndex": "0x1B4F",
            "parameterIndex": 4
        },
        {
            "gridIndex": "0x1BAF",
            "parameterIndex": 3
        },
        {
            "gridIndex": "0x1BBC",
            "parameterIndex": 4
        },
        {
            "gridIndex": "0x1BC3",
            "parameterIndex": 3
        },
        {
            "gridIndex": "0x1BC4",
            "parameterIndex": 13
        },
        {
            "gridIndex": "0x1BCF",
            "parameterIndex": 4
        },
        {
            "gridIndex": "0x1C2F",
            "parameterIndex": 3
        },
        {
            "gridIndex": "0x1C3C",
            "parameterIndex": 4
        },
        {
            "gridIndex": "0x1C44",
            "parameterIndex": 3
        },
        {
            "gridIndex": "0x1C4F",
            "parameterIndex": 2
        },
        {
            "gridIndex": "0x1C50",
            "parameterIndex": 1
        },
        {
            "gridIndex": "0x1C51",
            "parameterIndex": 2
        },
        {
            "gridIndex": "0x1CAF",
            "parameterIndex": 3
        },
        {
            "gridIndex": "0x1CBC",
            "parameterIndex": 4
        },
        {
            "gridIndex": "0x1CC3",
            "parameterIndex": 3
        },
        {
            "gridIndex": "0x1CC4",
            "parameterIndex": 7
        },
        {
            "gridIndex": "0x1CD1",
            "parameterIndex": 4
        },
        {
            "gridIndex": "0x1D2F",
            "parameterIndex": 3
        },
        {
            "gridIndex": "0x1D3C",
            "parameterIndex": 4
        },
        {
            "gridIndex": "0x1D43",
            "parameterIndex": 3
        },
        {
            "gridIndex": "0x1D51",
            "parameterIndex": 4
        },
        {
            "gridIndex": "0x1DAF",
            "parameterIndex": 3
        },
        {
            "gridIndex": "0x1DBC",
            "parameterIndex": 4
        },
        {
            "gridIndex": "0x1DC3",
            "parameterIndex": 3
        },
        {
            "gridIndex": "0x1DD1",
            "parameterIndex": 4
        },
        {
            "gridIndex": "0x1E2F",
            "parameterIndex": 3
        },
        {
            "gridIndex": "0x1E3C",
            "parameterIndex": 4
        },
        {
            "gridIndex": "0x1E43",
            "parameterIndex": 3
        },
        {
            "gridIndex": "0x1E51",
            "parameterIndex": 4
        },
        {
            "gridIndex": "0x1EAF",
            "parameterIndex": 3
        },
        {
            "gridIndex": "0x1EBC",
            "parameterIndex": 4
        },
        {
            "gridIndex": "0x1EC3",
            "parameterIndex": 3
        },
        {
            "gridIndex": "0x1EC4",
            "parameterIndex": 13
        },
        {
            "gridIndex": "0x1ED1",
            "parameterIndex": 4
        },
        {
            "gridIndex": "0x1F2F",
            "parameterIndex": 3
        },
        {
            "gridIndex": "0x1F3C",
            "parameterIndex": 4
        },
        {
            "gridIndex": "0x1F44",
            "parameterIndex": 14
        },
        {
            "gridIndex": "0x1F45",
            "parameterIndex": 13
        },
        {
            "gridIndex": "0x1F4B",
            "parameterIndex": 5
        },
        {
            "gridIndex": "0x1F4C",
            "parameterIndex": 11
        },
        {
            "gridIndex": "0x1F4D",
            "parameterIndex": 13
        },
        {
            "gridIndex": "0x1F51",
            "parameterIndex": 4
        },
        {
            "gridIndex": "0x1FAF",
            "parameterIndex": 3
        },
        {
            "gridIndex": "0x1FBC",
            "parameterIndex": 4
        },
        {
            "gridIndex": "0x1FC5",
            "parameterIndex": 11
        },
        {
            "gridIndex": "0x1FC6",
            "parameterIndex": 11
        },
        {
            "gridIndex": "0x1FC7",
            "parameterIndex": 11
        },
        {
            "gridIndex": "0x1FC8",
            "parameterIndex": 11
        },
        {
            "gridIndex": "0x1FC9",
            "parameterIndex": 11
        },
        {
            "gridIndex": "0x1FCA",
            "parameterIndex": 11
        },
        {
            "gridIndex": "0x1FCB",
            "parameterIndex": 11
        },
        {
            "gridIndex": "0x1FCD",
            "parameterIndex": 11
        },
        {
            "gridIndex": "0x1FCE",
            "parameterIndex": 11
        },
        {
            "gridIndex": "0x1FCF",
            "parameterIndex": 11
        },
        {
            "gridIndex": "0x1FD0",
            "parameterIndex": 11
        },
        {
            "gridIndex": "0x1FD1",
            "parameterIndex": 12
        },
        {
            "gridIndex": "0x202F",
            "parameterIndex": 3
        },
        {
            "gridIndex": "0x203C",
            "parameterIndex": 4
        },
        {
            "gridIndex": "0x20AF",
            "parameterIndex": 3
        },
        {
            "gridIndex": "0x20BC",
            "parameterIndex": 4
        },
        {
            "gridIndex": "0x212F",
            "parameterIndex": 3
        },
        {
            "gridIndex": "0x213C",
            "parameterIndex": 4
        },
        {
            "gridIndex": "0x21AF",
            "parameterIndex": 3
        },
        {
            "gridIndex": "0x21BC",
            "parameterIndex": 4
        },
        {
            "gridIndex": "0x222F",
            "parameterIndex": 3
        },
        {
            "gridIndex": "0x223C",
            "parameterIndex": 4
        },
        {
            "gridIndex": "0x22AF",
            "parameterIndex": 3
        },
        {
            "gridIndex": "0x22BC",
            "parameterIndex": 4
        },
        {
            "gridIndex": "0x232F",
            "parameterIndex": 3
        },
        {
            "gridIndex": "0x233C",
            "parameterIndex": 2
        },
        {
            "gridIndex": "0x233D",
            "parameterIndex": 1
        },
        {
            "gridIndex": "0x233E",
            "parameterIndex": 1
        },
        {
            "gridIndex": "0x233F",
            "parameterIndex": 1
        },
        {
            "gridIndex": "0x2340",
            "parameterIndex": 1
        },
        {
            "gridIndex": "0x2341",
            "parameterIndex": 1
        },
        {
            "gridIndex": "0x2342",
            "parameterIndex": 1
        },
        {
            "gridIndex": "0x2343",
            "parameterIndex": 1
        },
        {
            "gridIndex": "0x2344",
            "parameterIndex": 1
        },
        {
            "gridIndex": "0x2345",
            "parameterIndex": 1
        },
        {
            "gridIndex": "0x2346",
            "parameterIndex": 1
        },
        {
            "gridIndex": "0x2347",
            "parameterIndex": 1
        },
        {
            "gridIndex": "0x2348",
            "parameterIndex": 1
        },
        {
            "gridIndex": "0x2349",
            "parameterIndex": 1
        },
        {
            "gridIndex": "0x234A",
            "parameterIndex": 1
        },
        {
            "gridIndex": "0x234B",
            "parameterIndex": 1
        },
        {
            "gridIndex": "0x234C",
            "parameterIndex": 1
        },
        {
            "gridIndex": "0x234D",
            "parameterIndex": 1
        },
        {
            "gridIndex": "0x234E",
            "parameterIndex": 1
        },
        {
            "gridIndex": "0x234F",
            "parameterIndex": 1
        },
        {
            "gridIndex": "0x2350",
            "parameterIndex": 1
        },
        {
            "gridIndex": "0x2351",
            "parameterIndex": 2
        },
        {
            "gridIndex": "0x23AF",
            "parameterIndex": 3
        },
        {
            "gridIndex": "0x23D1",
            "parameterIndex": 4
        },
        {
            "gridIndex": "0x242F",
            "parameterIndex": 3
        },
        {
            "gridIndex": "0x2451",
            "parameterIndex": 4
        },
        {
            "gridIndex": "0x24AF",
            "parameterIndex": 3
        },
        {
            "gridIndex": "0x24D1",
            "parameterIndex": 4
        },
        {
            "gridIndex": "0x252F",
            "parameterIndex": 3
        },
        {
            "gridIndex": "0x2551",
            "parameterIndex": 4
        },
        {
            "gridIndex": "0x25AF",
            "parameterIndex": 3
        },
        {
            "gridIndex": "0x25D1",
            "parameterIndex": 4
        },
        {
            "gridIndex": "0x262F",
            "parameterIndex": 3
        },
        {
            "gridIndex": "0x2651",
            "parameterIndex": 4
        },
        {
            "gridIndex": "0x26AF",
            "parameterIndex": 3
        },
        {
            "gridIndex": "0x26D1",
            "parameterIndex": 4
        },
        {
            "gridIndex": "0x272F",
            "parameterIndex": 3
        },
        {
            "gridIndex": "0x2751",
            "parameterIndex": 4
        },
        {
            "gridIndex": "0x27AF",
            "parameterIndex": 3
        },
        {
            "gridIndex": "0x27D1",
            "parameterIndex": 4
        },
        {
            "gridIndex": "0x282F",
            "parameterIndex": 3
        },
        {
            "gridIndex": "0x2851",
            "parameterIndex": 4
        },
        {
            "gridIndex": "0x28AF",
            "parameterIndex": 3
        },
        {
            "gridIndex": "0x28B3",
            "parameterIndex": 12
        },
        {
            "gridIndex": "0x28B4",
            "parameterIndex": 11
        },
        {
            "gridIndex": "0x28B5",
            "parameterIndex": 11
        },
        {
            "gridIndex": "0x28B6",
            "parameterIndex": 11
        },
        {
            "gridIndex": "0x28B7",
            "parameterIndex": 11
        },
        {
            "gridIndex": "0x28B8",
            "parameterIndex": 11
        },
        {
            "gridIndex": "0x28B9",
            "parameterIndex": 11
        },
        {
            "gridIndex": "0x28BA",
            "parameterIndex": 11
        },
        {
            "gridIndex": "0x28BB",
            "parameterIndex": 11
        },
        {
            "gridIndex": "0x28BC",
            "parameterIndex": 11
        },
        {
            "gridIndex": "0x28BD",
            "parameterIndex": 11
        },
        {
            "gridIndex": "0x28BE",
            "parameterIndex": 11
        },
        {
            "gridIndex": "0x28BF",
            "parameterIndex": 11
        },
        {
            "gridIndex": "0x28C0",
            "parameterIndex": 11
        },
        {
            "gridIndex": "0x28C1",
            "parameterIndex": 11
        },
        {
            "gridIndex": "0x28C2",
            "parameterIndex": 11
        },
        {
            "gridIndex": "0x28C3",
            "parameterIndex": 11
        },
        {
            "gridIndex": "0x28C4",
            "parameterIndex": 11
        },
        {
            "gridIndex": "0x28C5",
            "parameterIndex": 11
        },
        {
            "gridIndex": "0x28C6",
            "parameterIndex": 11
        },
        {
            "gridIndex": "0x28C7",
            "parameterIndex": 11
        },
        {
            "gridIndex": "0x28C8",
            "parameterIndex": 11
        },
        {
            "gridIndex": "0x28C9",
            "parameterIndex": 11
        },
        {
            "gridIndex": "0x28CA",
            "parameterIndex": 11
        },
        {
            "gridIndex": "0x28CB",
            "parameterIndex": 11
        },
        {
            "gridIndex": "0x28CC",
            "parameterIndex": 11
        },
        {
            "gridIndex": "0x28CD",
            "parameterIndex": 11
        },
        {
            "gridIndex": "0x28CE",
            "parameterIndex": 11
        },
        {
            "gridIndex": "0x28CF",
            "parameterIndex": 11
        },
        {
            "gridIndex": "0x28D0",
            "parameterIndex": 11
        },
        {
            "gridIndex": "0x28D1",
            "parameterIndex": 12
        },
        {
            "gridIndex": "0x292F",
            "parameterIndex": 3
        },
        {
            "gridIndex": "0x2933",
            "parameterIndex": 4
        },
        {
            "gridIndex": "0x29AF",
            "parameterIndex": 3
        },
        {
            "gridIndex": "0x29B3",
            "parameterIndex": 4
        },
        {
            "gridIndex": "0x2A2F",
            "parameterIndex": 10
        },
        {
            "gridIndex": "0x2A30",
            "parameterIndex": 11
        },
        {
            "gridIndex": "0x2A31",
            "parameterIndex": 11
        },
        {
            "gridIndex": "0x2A32",
            "parameterIndex": 11
        },
        {
            "gridIndex": "0x2A33",
            "parameterIndex": 12
        }
    ],
    "parameters": [
        {
            "z": 0,
            "height": 8,
            "shape": 8,
            "id": 0
        },
        {
            "z": 0,
            "height": 8,
            "shape": 4,
            "id": 0
        },
        {
            "z": 0,
            "height": 8,
            "shape": 7,
            "id": 0
        },
        {
            "z": 0,
            "height": 8,
            "shape": 2,
            "id": 0
        },
        {
            "z": 0,
            "height": 8,
            "shape": 1,
            "id": 0
        },
        {
            "z": 0,
            "height": 8,
            "shape": 9,
            "id": 0
        },
        {
            "z": 0,
            "height": 8,
            "shape": 16,
            "id": 0
        },
        {
            "z": 0,
            "height": 8,
            "shape": 12,
            "id": 0
        },
        {
            "z": 0,
            "height": 8,
            "shape": 11,
            "id": 0
        },
        {
            "z": 0,
            "height": 8,
            "shape": 15,
            "id": 0
        },
        {
            "z": 0,
            "height": 8,
            "shape": 6,
            "id": 0
        },
        {
            "z": 0,
            "height": 8,
            "shape": 3,
            "id": 0
        },
        {
            "z": 0,
            "height": 8,
            "shape": 5,
            "id": 0
        },
        {
            "z": 0,
            "height": 8,
            "shape": 10,
            "id": 0
        },
        {
            "z": 0,
            "height": 8,
            "shape": 14,
            "id": 0
        }
    ]
}